{
    "depressed mood": [
        0.24,
        0.24,
        0.24,
        0.24
    ],
    "low self-esteem": [
        0.24,
        0.24,
        0.24,
        0.24
    ],
    "negativity bias": [
        0.24,
        0.24,
        0.24,
        0.24
    ],
    "guilt": [
        0.24,
        0.24,
        0.24,
        0.24
    ],
    "risk-aversion": [
        0.32,
        0.32,
        0.32,
        0.32
    ],
    "self-destruction": [
        0.24,
        0.24,
        0.24,
        0.24
    ],
    "manic mood": [
        0.24,
        0.24,
        0.24,
        0.24
    ],
    "grandiosity": [
        0.24,
        0.24,
        0.24,
        0.24
    ],
    "positivity bias": [
        0.24,
        0.24,
        0.24,
        0.24
    ],
    "lack of remorse": [
        0.32,
        0.32,
        0.32,
        0.32
    ],
    "risk-seeking": [
        0.24,
        0.24,
        0.24,
        0.24
    ],
    "hostility": [
        0.24,
        0.24,
        0.24,
        0.24
    ]
}